ipython_clipboard/__init__.py
IPythonClipboard-1.0b2.dist-info/LICENSE
IPythonClipboard-1.0b2.dist-info/METADATA
IPythonClipboard-1.0b2.dist-info/WHEEL
IPythonClipboard-1.0b2.dist-info/top_level.txt
IPythonClipboard-1.0b2.dist-info/RECORD
