Metadata-Version: 2.1
Name: IPythonClipboard
Version: 1.0b2
Summary: An IPython extension to copy and/or pickle input/output lines or variables.
Home-page: https://github.com/CarlosGTrejo/ipython_extensions/tree/master/ipython_clipboard
Author: Carlos G. Trejo
Author-email: carlos.guadarrama.trejo@gmail.com
License: MIT
Keywords: ipython clipboard clip utility utilities tools copy paste
Platform: UNKNOWN
Classifier: Development Status :: 4 - Beta
Classifier: Intended Audience :: Developers
Classifier: Framework :: IPython
Classifier: Programming Language :: Python :: 3
Classifier: License :: OSI Approved :: MIT License
Classifier: Operating System :: OS Independent
Classifier: Topic :: Utilities
Requires-Dist: ipython
Requires-Dist: pyperclip
